hydro/__init__.py
hydro/cli.py
hydro/files.py
hydro/logging.py
hydro/md5.py
hydro_cli-1.0.2.dist-info/LICENSE
hydro_cli-1.0.2.dist-info/METADATA
hydro_cli-1.0.2.dist-info/WHEEL
hydro_cli-1.0.2.dist-info/entry_points.txt
hydro_cli-1.0.2.dist-info/top_level.txt
hydro_cli-1.0.2.dist-info/RECORD
