Metadata-Version: 2.2
Name: hydro-cli
Version: 1.0.2
Summary: MD5 hash cracker
Requires-Python: >=3.13
License-File: LICENSE
Requires-Dist: click>=8.1.8
Requires-Dist: rich>=13.9.4
